{"cameraMode":{"drawMode":0,"name":"Shaded","section":"Shading Mode"},"sceneLighting":true,"audioPlay":false,"sceneViewState":{"m_AlwaysRefresh":false,"showFog":true,"showSkybox":true,"showFlares":true,"showImageEffects":true,"showParticleSystems":true,"showVisualEffectGraphs":true,"m_FxEnabled":true},"in2DMode":false,"pivot":{"x":-9.182737350463868,"y":2.375347375869751,"z":-7.355925559997559},"rotation":{"x":-0.15253674983978272,"y":-0.4241727590560913,"z":0.07273881882429123,"w":-0.8896580934524536},"size":1.3951221704483033,"orthographic":true}